pyctapi/__init__.py
pyctapi/apis/__init__.py
pyctapi/apis/base.py
pyctapi/apis/iam.py
pyctapi/apis/monitor.py
pyctapi/auth.py
pyctapi/exceptions.py
pyctapi/params/__init__.py
pyctapi/params/common.py
pyctapi/transport.py
pyctapi-0.1.2.dist-info/WHEEL
pyctapi-0.1.2.dist-info/METADATA
pyctapi-0.1.2.dist-info/RECORD
